odoo/addons/sale_channel/README.rst
odoo/addons/sale_channel/__init__.py
odoo/addons/sale_channel/__manifest__.py
odoo/addons/sale_channel/demo/demo.xml
odoo/addons/sale_channel/i18n/it.po
odoo/addons/sale_channel/i18n/sale_channel.pot
odoo/addons/sale_channel/models/__init__.py
odoo/addons/sale_channel/models/account_move.py
odoo/addons/sale_channel/models/sale_channel.py
odoo/addons/sale_channel/models/sale_channel_owner.py
odoo/addons/sale_channel/models/sale_order.py
odoo/addons/sale_channel/readme/CONTRIBUTORS.md
odoo/addons/sale_channel/readme/CREDITS.md
odoo/addons/sale_channel/readme/DESCRIPTION.md
odoo/addons/sale_channel/security/ir.model.access.csv
odoo/addons/sale_channel/static/description/icon.png
odoo/addons/sale_channel/static/description/index.html
odoo/addons/sale_channel/tests/__init__.py
odoo/addons/sale_channel/tests/test_sale_channel.py
odoo/addons/sale_channel/views/account_move_view.xml
odoo/addons/sale_channel/views/sale_channel_view.xml
odoo/addons/sale_channel/views/sale_order_view.xml
odoo_addon_sale_channel-18.0.1.0.0.3.dist-info/METADATA
odoo_addon_sale_channel-18.0.1.0.0.3.dist-info/WHEEL
odoo_addon_sale_channel-18.0.1.0.0.3.dist-info/top_level.txt
odoo_addon_sale_channel-18.0.1.0.0.3.dist-info/RECORD
